owlman/__init__.py
owlman/bond_helper.py
owlman/kis_trading.py
owlman/naver_finance.py
owlman/trading_helper.py
owlman-0.6.5.dist-info/METADATA
owlman-0.6.5.dist-info/WHEEL
owlman-0.6.5.dist-info/top_level.txt
owlman-0.6.5.dist-info/RECORD
