Metadata-Version: 2.1
Name: owlman
Version: 0.6.5
Summary: 금융 분석을 위한 툴 모음
Home-page: https://github.com/qus0in/owlman
Author: qus0in
Author-email: qus0in@gmail.com
Keywords: owlman
Requires-Python: >=3.6
Requires-Dist: requests
Requires-Dist: pandas
Requires-Dist: plotly
Requires-Dist: scikit-learn
